CHANGELOG.rst
MANIFEST.in
README.rst
TODO.txt
VERSION.txt
setup.cfg
setup.py
hg_fingerprint/__init__.py
hg_fingerprint.egg-info/PKG-INFO
hg_fingerprint.egg-info/SOURCES.txt
hg_fingerprint.egg-info/dependency_links.txt
hg_fingerprint.egg-info/requires.txt
hg_fingerprint.egg-info/top_level.txt
hg_fingerprint.egg-info/zip-safe
hg_fingerprint/test/__init__.py
hg_fingerprint/test/test_fingerprint.py