Metadata-Version: 2.1
Name: hg-fingerprint
Version: 0.1.6
Summary: Better archive fingerprint file composition.
Home-page: https://bitbucket.org/metagriffin/hg-fingerprint
Author: metagriffin
Author-email: mg.pypi@uberdev.org
License: GPLv3+
Keywords: mercurial hg version control archive fingerprint text json yaml xml
Platform: any
Classifier: Development Status :: 4 - Beta
Classifier: Environment :: Console
Classifier: Intended Audience :: Developers
Classifier: Natural Language :: English
Classifier: Operating System :: OS Independent
Classifier: Programming Language :: Python
Classifier: Topic :: Software Development
Classifier: Topic :: Software Development :: Version Control
Classifier: Topic :: Utilities
Classifier: License :: OSI Approved :: GNU General Public License v3 or later (GPLv3+)
Provides-Extra: yaml
